Metadata-Version: 2.4
Name: m-eclipses
Version: 0.4.0
Summary: MSSL Emission Calculation and Line Intensity Prediction for SOLAR-C EUVST-SW
Home-page: https://github.com/jamesmckevitt/solc_euvst_sw_response
Author: James McKevitt
Author-email: James McKevitt <jm2@mssl.ucl.ac.uk>
License: Contact for permission
Project-URL: Homepage, https://github.com/jamesmckevitt/solc_euvst_sw_response
Project-URL: Repository, https://github.com/jamesmckevitt/solc_euvst_sw_response
Classifier: Development Status :: 4 - Beta
Classifier: Intended Audience :: Science/Research
Classifier: Topic :: Scientific/Engineering :: Astronomy
Classifier: Programming Language :: Python :: 3
Classifier: Programming Language :: Python :: 3.8
Classifier: Programming Language :: Python :: 3.9
Classifier: Programming Language :: Python :: 3.10
Classifier: Programming Language :: Python :: 3.11
Requires-Python: >=3.8
License-File: LICENSE
Requires-Dist: numpy
Requires-Dist: astropy
Requires-Dist: ndcube
Requires-Dist: specutils
Requires-Dist: scipy
Requires-Dist: matplotlib
Requires-Dist: joblib
Requires-Dist: tqdm
Requires-Dist: dill
Requires-Dist: pyyaml
Requires-Dist: reproject
Requires-Dist: sunpy[all]
Provides-Extra: dev
Requires-Dist: pytest; extra == "dev"
Requires-Dist: black; extra == "dev"
Requires-Dist: flake8; extra == "dev"
Requires-Dist: mypy; extra == "dev"
Dynamic: author
Dynamic: home-page
Dynamic: license-file
Dynamic: requires-python
